aglio/__init__.py
aglio/aglio.py
aglio/coordinate_transformations.py
aglio/data_manager.py
aglio/mapping.py
aglio/point_data.py
aglio/typing.py
aglio/_utilities/__init__.py
aglio/_utilities/dependencies.py
aglio/_utilities/logger.py
aglio/_utilities/testing.py
aglio/geo_points/__init__.py
aglio/geo_points/datasets.py
aglio/sample_data/__init__.py
aglio/seismology/__init__.py
aglio/seismology/collections.py
aglio/seismology/datasets.py
aglio/seismology/stats.py
aglio/tests/__init__.py
aglio/tests/test_aglio.py
aglio/tests/test_coordinate_transformations.py
aglio/tests/test_data_manager.py
aglio/tests/test_dependencies.py
aglio/tests/test_echem.py
aglio/tests/test_etopo.py
aglio/tests/test_kmeans.py
aglio/tests/test_point_data.py
aglio/tests/test_polygon_file.py
aglio/tests/test_seismic_refmodels.py
aglio/tests/test_testing.py
aglio/topography/__init__.py
aglio/topography/etopo.py
aglio-0.2.0.dist-info/LICENSE
aglio-0.2.0.dist-info/METADATA
aglio-0.2.0.dist-info/WHEEL
aglio-0.2.0.dist-info/top_level.txt
aglio-0.2.0.dist-info/RECORD
